setup.py
bin/swf_decider_server.py
bin/swf_worker_server.py
luigi_swf/__init__.py
luigi_swf/cw.py
luigi_swf/decider.py
luigi_swf/executor.py
luigi_swf/tasks.py
luigi_swf/util.py
luigi_swf/worker.py
luigi_swf.egg-info/PKG-INFO
luigi_swf.egg-info/SOURCES.txt
luigi_swf.egg-info/dependency_links.txt
luigi_swf.egg-info/pbr.json
luigi_swf.egg-info/requires.txt
luigi_swf.egg-info/top_level.txt
test/test_decider.py
test/test_util.py